abletonosc_client/__init__.py
abletonosc_client/application.py
abletonosc_client/browser.py
abletonosc_client/chords.py
abletonosc_client/client.py
abletonosc_client/clip.py
abletonosc_client/clip_slot.py
abletonosc_client/device.py
abletonosc_client/midimap.py
abletonosc_client/scales.py
abletonosc_client/scene.py
abletonosc_client/song.py
abletonosc_client/tests/__init__.py
abletonosc_client/tests/conftest.py
abletonosc_client/tests/test_application.py
abletonosc_client/tests/test_chords.py
abletonosc_client/tests/test_client.py
abletonosc_client/tests/test_clip.py
abletonosc_client/tests/test_clip_slot.py
abletonosc_client/tests/test_device.py
abletonosc_client/tests/test_midimap.py
abletonosc_client/tests/test_scales.py
abletonosc_client/tests/test_scene.py
abletonosc_client/tests/test_song.py
abletonosc_client/tests/test_track.py
abletonosc_client/tests/test_view.py
abletonosc_client/track.py
abletonosc_client/view.py
abletonosc_client-1.1.0.dist-info/LICENSE
abletonosc_client-1.1.0.dist-info/METADATA
abletonosc_client-1.1.0.dist-info/WHEEL
abletonosc_client-1.1.0.dist-info/RECORD
