Metadata-Version: 2.3
Name: abletonosc-client
Version: 1.1.0
Summary: Python OSC client wrapper for AbletonOSC - control Ableton Live via OSC
License: MIT
Keywords: ableton,osc,music,midi,live
Author: ldraney
Requires-Python: >=3.11
Classifier: Development Status :: 5 - Production/Stable
Classifier: Intended Audience :: Developers
Classifier: License :: OSI Approved :: MIT License
Classifier: Operating System :: OS Independent
Classifier: Programming Language :: Python :: 3
Classifier: Programming Language :: Python :: 3.11
Classifier: Programming Language :: Python :: 3.12
Classifier: Programming Language :: Python :: 3.13
Classifier: Topic :: Multimedia :: Sound/Audio
Classifier: Topic :: Software Development :: Libraries :: Python Modules
Requires-Dist: python-osc (>=1.8.0)
Project-URL: Homepage, https://github.com/ldraney/abletonosc-client
Project-URL: Repository, https://github.com/ldraney/abletonosc-client
